sysrev/__init__.py
sysrev/client.py
sysrev-1.3.13.dist-info/METADATA
sysrev-1.3.13.dist-info/WHEEL
sysrev-1.3.13.dist-info/top_level.txt
sysrev-1.3.13.dist-info/RECORD
