Metadata-Version: 2.2
Name: sysrev
Version: 1.3.13
Summary: get sysrev project data and use the sysrev api
Home-page: https://github.com/sysrev/PySysrev
Author: Thomas Luechtefeld
Author-email: tom@insilica.co
Requires-Python: >=3.6
Requires-Dist: requests
Dynamic: author
Dynamic: author-email
Dynamic: description
Dynamic: description-content-type
Dynamic: home-page
Dynamic: requires-dist
Dynamic: requires-python
Dynamic: summary
